[
	{
		"__TYPE__": "SharedSliceContent",
		"variation": "default",
		"primary": {
			"title": {
				"__TYPE__": "FieldContent",
				"value": "key",
				"type": "Text"
			},
			"body": {
				"__TYPE__": "FieldContent",
				"value": "game",
				"type": "Text"
			},
			"background": {
				"__TYPE__": "BooleanContent",
				"value": true
			}
		},
		"items": [
			{
				"__TYPE__": "GroupItemContent",
				"value": [
					[
						"cta_title",
						{
							"__TYPE__": "FieldContent",
							"value": "future",
							"type": "Text"
						}
					],
					[
						"cta_url",
						{
							"__TYPE__": "LinkContent",
							"value": {
								"__TYPE__": "ExternalLink",
								"url": "https://slicemachine.dev"
							}
						}
					]
				]
			}
		]
	},
	{
		"__TYPE__": "SharedSliceContent",
		"variation": "centered",
		"primary": {
			"title": {
				"__TYPE__": "FieldContent",
				"value": "black",
				"type": "Text"
			},
			"body": {
				"__TYPE__": "FieldContent",
				"value": "wing",
				"type": "Text"
			},
			"background": {
				"__TYPE__": "BooleanContent",
				"value": false
			}
		},
		"items": [
			{
				"__TYPE__": "GroupItemContent",
				"value": [
					[
						"cta_title",
						{
							"__TYPE__": "FieldContent",
							"value": "happy",
							"type": "Text"
						}
					],
					[
						"cta_url",
						{
							"__TYPE__": "LinkContent",
							"value": {
								"__TYPE__": "ExternalLink",
								"url": "https://prismic.io"
							}
						}
					]
				]
			}
		]
	}
]